libtfr.cpython-37m-x86_64-linux-gnu.so
libtfr-2.1.9.dist-info/METADATA
libtfr-2.1.9.dist-info/RECORD
libtfr-2.1.9.dist-info/WHEEL
libtfr-2.1.9.dist-info/COPYING
libtfr-2.1.9.dist-info/top_level.txt
libtfr.libs/libgfortran-e686bd2c.so.5.0.0
libtfr.libs/libblas-cd6951ff.so.3.12.0
libtfr.libs/libfftw3-14f8490b.so.3.6.10
libtfr.libs/liblapack-89443c7f.so.3.12.0
libtfr.libs/libquadmath-9b5eedf9.so.0.0.0
libtfr.libs/libgcc_s-a3a07607.so.1
