Metadata-Version: 2.1
Name: libtfr
Version: 2.1.9
Summary: Calculates multi-taper windowed and time-frequency reassignment spectrograms
Home-page: https://github.com/melizalab/libtfr
Author: Dan Meliza
Author-email: dan@meliza.org
Maintainer: Dan Meliza
Maintainer-email: dan@meliza.org
License: GNU General Public License (GPL)
Classifier: Development Status :: 5 - Production/Stable
Classifier: Intended Audience :: Science/Research
Classifier: License :: OSI Approved :: GNU General Public License (GPL)
Classifier: Programming Language :: Python
Classifier: Programming Language :: Python :: 3.7
Classifier: Programming Language :: Python :: 3.8
Classifier: Programming Language :: Python :: 3.9
Classifier: Programming Language :: Python :: 3.10
Classifier: Programming Language :: Python :: 3.11
Classifier: Programming Language :: Python :: 3.12
Classifier: Programming Language :: Python :: Implementation :: CPython
Classifier: Programming Language :: Python :: Implementation :: PyPy
Classifier: Topic :: Scientific/Engineering
Classifier: Operating System :: Unix
Classifier: Operating System :: POSIX :: Linux
Classifier: Operating System :: MacOS :: MacOS X
Classifier: Natural Language :: English
Requires-Python: >=3.7
License-File: COPYING
Requires-Dist: numpy >=1.21
Provides-Extra: test
Requires-Dist: pytest >=7.0 ; extra == 'test'
